artd_product/__init__.py
artd_product/admin.py
artd_product/apps.py
artd_product/models.py
artd_product/signals.py
artd_product/tests.py
artd_product/views.py
artd_product/data/__init__.py
artd_product/data/taxes.py
artd_product/locale/__init__.py
artd_product/locale/en/__init__.py
artd_product/locale/en/LC_MESSAGES/django.po
artd_product/locale/es/__init__.py
artd_product/locale/es/LC_MESSAGES/django.po
artd_product/management/__init__.py
artd_product/management/commands/__init__.py
artd_product/management/commands/create_taxes.py
artd_product/migrations/0001_initial.py
artd_product/migrations/0002_brand_external_id_brand_json_data_brand_source_and_more.py
artd_product/migrations/0003_alter_product_brand.py
artd_product/migrations/0004_groupedproduct_variations.py
artd_product/migrations/0005_product_variations.py
artd_product/migrations/0006_alter_category_banner_image_and_more.py
artd_product/migrations/0007_alter_brand_created_at_alter_brand_updated_at_and_more.py
artd_product/migrations/0008_remove_productimage_alt_alter_productimage_image.py
artd_product/migrations/0009_product_partner.py
artd_product/migrations/0010_groupedproduct_partner.py
artd_product/migrations/0011_category_secondary_mini_image_and_more.py
artd_product/migrations/0012_rootcategory_secondary_mini_image.py
artd_product/migrations/0013_rename_secondary_mini_image_category_secondary_mini_image.py
artd_product/migrations/0014_categorybyurl.py
artd_product/migrations/0015_categorybyurl_url_path_alter_categorybyurl_url.py
artd_product/migrations/0016_tax_partner.py
artd_product/migrations/0017_remove_tax_partner_brand_partner.py
artd_product/migrations/0018_alter_brand_meta_description_and_more.py
artd_product/migrations/__init__.py
artd_product/utils/__init__.py
artd_product/utils/product_util.py
product/__init__.py
product/asgi.py
product/settings.py
product/urls.py
product/wsgi.py
artd_product-1.0.22.dist-info/LICENSE
artd_product-1.0.22.dist-info/METADATA
artd_product-1.0.22.dist-info/WHEEL
artd_product-1.0.22.dist-info/top_level.txt
artd_product-1.0.22.dist-info/RECORD
